OpenHosta/__init__.py
OpenHosta/asynchrone/__init__.py
OpenHosta/core/__init__.py
OpenHosta/core/analizer.py
OpenHosta/core/config.py
OpenHosta/core/inspection.py
OpenHosta/core/logger.py
OpenHosta/core/meta_prompt.py
OpenHosta/core/pydantic_proxy.py
OpenHosta/core/type_converter.py
OpenHosta/exec/__init__.py
OpenHosta/exec/ask.py
OpenHosta/exec/closure.py
OpenHosta/exec/emulate.py
OpenHosta/models/OpenAICompatible.py
OpenHosta/models/__init__.py
OpenHosta/models/base_model.py
OpenHosta/pipelines/__init__.py
OpenHosta/pipelines/simple_pipeline.py
OpenHosta/semantics/operators.py
OpenHosta/utils/__init__.py
OpenHosta/utils/errors.py
OpenHosta/utils/import_handler.py
openhosta-3.0.3.dist-info/licenses/LICENSE
openhosta-3.0.3.dist-info/METADATA
openhosta-3.0.3.dist-info/WHEEL
openhosta-3.0.3.dist-info/top_level.txt
openhosta-3.0.3.dist-info/RECORD
