Metadata-Version: 2.4
Name: OpenHosta
Version: 3.0.3
Summary: A lightweight library integrating LLM natively into Python
Author: Léandre Ramos, Merlin Devillard, William Jolivet, Emmanuel Batt
License: MIT License
Project-URL: Homepage, https://github.com/hand-e-fr/OpenHosta
Project-URL: Issues, https://github.com/hand-e-fr/OpenHosta/issues
Keywords: AI,GPT,Natural language,Autommatic,Easy
Classifier: Development Status :: 5 - Production/Stable
Classifier: Programming Language :: Python
Classifier: Programming Language :: Python :: 3
Classifier: Programming Language :: Python :: 3.8
Classifier: Programming Language :: Python :: 3.9
Classifier: Programming Language :: Python :: 3.10
Classifier: Programming Language :: Python :: 3.11
Classifier: Programming Language :: Python :: 3.12
Classifier: Programming Language :: Python :: 3.13
Classifier: Programming Language :: Python :: 3.14
Classifier: Programming Language :: Python :: Implementation :: CPython
Classifier: License :: OSI Approved :: MIT License
Classifier: Operating System :: OS Independent
Classifier: Intended Audience :: Developers
Classifier: Intended Audience :: Science/Research
Classifier: Intended Audience :: Education
Classifier: Natural Language :: French
Classifier: Natural Language :: English
Classifier: Topic :: Software Development :: Code Generators
Classifier: Topic :: Scientific/Engineering
Classifier: Topic :: Scientific/Engineering :: Artificial Intelligence
Classifier: Topic :: Software Development :: Libraries
Classifier: Typing :: Typed
Requires-Python: <=3.14,>=3.8
License-File: LICENSE
Requires-Dist: requests>=2.32.3
Requires-Dist: typing_extensions>=4.12.2
Requires-Dist: jinja2>=3.1.5
Requires-Dist: python-dotenv>=1.1.1
Provides-Extra: dev
Requires-Dist: mypy>=1.13.0; extra == "dev"
Requires-Dist: isort>=5.13.2; extra == "dev"
Requires-Dist: autopep8>=2.3.1; extra == "dev"
Requires-Dist: pylint>=3.3.1; extra == "dev"
Requires-Dist: pyflakes>=3.2.0; extra == "dev"
Requires-Dist: bandit>=1.7.10; extra == "dev"
Provides-Extra: tests
Requires-Dist: pytest>=8.3.2; extra == "tests"
Requires-Dist: pytest-cov>=5.0.0; extra == "tests"
Requires-Dist: pillow>=11.0.0; extra == "tests"
Requires-Dist: pydantic>=2.8.2; extra == "tests"
Requires-Dist: Flask>=3.0.3; extra == "tests"
Dynamic: license-file
